trd_cea/__init__.py
trd_cea/plotting/__init__.py
trd_cea_toolkit-0.4.0.dist-info/licenses/LICENSE
trd_cea_toolkit-0.4.0.dist-info/METADATA
trd_cea_toolkit-0.4.0.dist-info/WHEEL
trd_cea_toolkit-0.4.0.dist-info/entry_points.txt
trd_cea_toolkit-0.4.0.dist-info/top_level.txt
trd_cea_toolkit-0.4.0.dist-info/RECORD
